README.md
helga_twitter.py
setup.py
helga_twitter.egg-info/PKG-INFO
helga_twitter.egg-info/SOURCES.txt
helga_twitter.egg-info/dependency_links.txt
helga_twitter.egg-info/entry_points.txt
helga_twitter.egg-info/requires.txt
helga_twitter.egg-info/top_level.txt
helga_twitter.egg-info/zip-safe