Metadata-Version: 1.1
Name: helga-twitter
Version: 0.4.3
Summary: twitter via irc
Home-page: https://github.com/bigjust/helga-twitter
Author: Justin Caratzas
Author-email: bigjust@lambdaphil.es
License: GPLv3
Keywords: helga twitter
Platform: UNKNOWN
Classifier: Development Status :: 4 - Beta
Classifier: License :: OSI Approved :: GNU General Public License v3 (GPLv3)
Classifier: Operating System :: OS Independent
Classifier: Programming Language :: Python
Classifier: Topic :: Software Development :: Libraries :: Python Modules
